fast_hypo_client/__init__.py
fast_hypo_client/api/__init__.py
fast_hypo_client/api/non_lin_loc/__init__.py
fast_hypo_client/api/non_lin_loc/locate_nlloc_locate_nlloc_post.py
fast_hypo_client/client.py
fast_hypo_client/models/__init__.py
fast_hypo_client/models/first_motion.py
fast_hypo_client/models/horizontal_uncertainty.py
fast_hypo_client/models/http_validation_error.py
fast_hypo_client/models/location_request_nl_loc.py
fast_hypo_client/models/onset.py
fast_hypo_client/models/origin.py
fast_hypo_client/models/phase_descriptor_p.py
fast_hypo_client/models/phase_descriptor_s.py
fast_hypo_client/models/phase_reading.py
fast_hypo_client/models/station_lat_lng.py
fast_hypo_client/models/validation_error.py
fast_hypo_client/models/velocity_layer_1d.py
fast_hypo_client/models/velocity_model_1d.py
fast_hypo_client/py.typed
fast_hypo_client/types.py
fast_hypo_client-0.1.3.dist-info/WHEEL
fast_hypo_client-0.1.3.dist-info/METADATA
fast_hypo_client-0.1.3.dist-info/RECORD
